  <page>
    <title>北星ゴム工業</title>
    <ns>0</ns>
    <id>1004779</id>
    <revision>
      <id>71546405</id>
      <parentid>65043459</parentid>
      <timestamp>2019-02-05T06:00:11Z</timestamp>
      <contributor>
        <username>Bb kishi077</username>
        <id>1445937</id>
      </contributor>
      <model>wikitext</model>
      <format>text/x-wiki</format>
      <text xml:space="preserve">{{出典の明記|date=2014年8月21日 (木) 17:38 (UTC)}}
{{画像提供依頼|date=2014年8月21日 (木) 17:38 (UTC)|cat=黒部市|本社外観}}
{{基礎情報 会社
 | 社名 = 北星ゴム工業株式会社
 | 英文社名 = Hokusei Rubber Industry Co., Ltd.
 | ロゴ =
 | 種類 = [[株式会社 (日本)|株式会社]]
 | 市場情報 =
 | 略称 = HRC
 | 国籍 = {{JPN}}
 | 郵便番号 = 938-0054
 | 本社所在地 = [[富山県]][[黒部市]]岡362番地14号&lt;br /&gt;{{ウィキ座標2段度分秒|36|51|50.4|N|137|25|45.7|E|region:JP|display=inline,title}}
 | 設立 = [[1948年]]
 | 業種 = 3350
 | 統一金融機関コード =
 | SWIFTコード =
 | 事業内容 =
 | 代表者 = 米屋正弘
 | 資本金 = 4600万円
 | 売上高 =
 | 総資産 =
 | 従業員数 = 442名
 | 決算期 = 7月
 | 主要株主 =
 | 主要子会社 =
 | 関係する人物 =
 | 外部リンク = [http://www.hokusay-rubber.co.jp/ 公式ウエブサイト]
 | 特記事項 =
}}

'''北星ゴム工業株式会社'''（ほくせいゴムこうぎょう）は、1930年に設立された日本のゴム製品メーカー。[[富山県]][[黒部市]]の本社工場のほか、[[入善町]]に第2工場を、東京、大阪、名古屋に営業所を置く。
&lt;!--
本社内には、食堂、売店、浴場、屋内競技設備を備えた、厚生会館がある。--&gt;

==沿革==
*[[1930年]] - 北星ゴム生地工業の名称で創業。総ゴム履物の生産を開始する。当時は[[生地町]]（後の黒部市生地地区）に工場があった。
*[[1948年]] - 北星ゴム工業株式会社に改称。
*[[1960年]] - JIS許可工場となる。
*[[1972年]] - 総ゴム履物部を廃止。全面的に工業用ゴム製品に転換。
*[[1976年]] - 建材用ゴム部品の生産を開始。
*[[1986年]] - 現在地に工場を新築移転。
*[[1989年]] - 建材試験センターを建設。
*[[1992年]] - 入善町に第2工場を置く。
*[[1997年]] - 国土交通省より乙種防火戸用難燃性CRゴムガスケットの認定書を受領。
*[[1998年]] - 国土交通省より耐火環状目的ガスケットの指定書を受領。
*[[2003年]] - テクニカルセンターを建設。
*[[2004年]] - ISO9001:2000認証取得（2月）
　　　　　　　　 ISO14001:2004認証取得（12月）
*[[2007年]] - 経済産業省「2007年度版元気なモノ作り中小企業300社」に選定。
*[[2018年]] - 経済的、社会的に優れた成果を挙げている企業を表彰する「グッドカンパニー大賞」の優秀企業賞を受賞&lt;ref&gt;[https://www.chukiken.or.jp/citation/list_h28.html#h30 グッドカンパニー大賞平成30年度受賞企業|||公益社団法人中小企業研究センター|||]&lt;/ref&gt;

==事業内容==
自動車関連のゴム製品をメインに、建材関連ゴム製品、新幹線の窓枠のゴム製品、電気・電子機器用ゴム製品などを手がける。製品の中には日本国内[[シェア]]の高い製品も多い。

*[[高速道路]]の[[道路標識|標識]] 
*道路標識筒（[[ロードコーン|ラバーコーン]]） - 日本国内シェア90%&lt;ref&gt;[http://www.chusho.meti.go.jp/keiei/sapoin/monozukuri300sha19fy/4chuubu/19toyama_05.html 中小企業庁：元気なモノ作り中小企業300社]&lt;/ref&gt;&lt;!--（ここでの売り上げは4%）--&gt;
*ゴム製路上標識
また、建材関連ゴム製品については、以下の建物に使用されている。
*[[秋葉原ダイビル]]
*[[さいたまスーパーアリーナ]]
*[[九段第一合同庁舎]]（[[千代田区|千代田区役所]]）

==脚注==
{{Reflist}}
== 外部リンク ==
*[http://www.hokusay-rubber.co.jp/ 公式ウエブサイト]

{{DEFAULTSORT:ほくせいこむこうきよう}}
[[Category:日本のゴム製品メーカー]]
[[Category:黒部市の企業]]
{{Company-stub}}</text>
      <sha1>tiuujcfax07km1p0qeuyiwpi631yuft</sha1>
    </revision>
  </page>
